oilprop/__init__.py
oilprop/volumetric_thermal_expansion_coefficient.py
oilprop-0.0.1.dist-info/LICENSE
oilprop-0.0.1.dist-info/METADATA
oilprop-0.0.1.dist-info/WHEEL
oilprop-0.0.1.dist-info/top_level.txt
oilprop-0.0.1.dist-info/RECORD
